{
  "directed": false,
  "multigraph": false,
  "graph": {},
  "nodes": [
    {
      "entity_type": "club",
      "id": "Chicago Fire FC"
    },
    {
      "entity_type": "club",
      "id": "D.C. United"
    },
    {
      "entity_type": "club",
      "id": "Real Salt Lake"
    },
    {
      "entity_type": "club",
      "id": "Sporting Kansas City"
    }
  ],
  "edges": [
    {
      "weight": 2,
      "article_count": 2,
      "source": "Chicago Fire FC",
      "target": "D.C. United"
    },
    {
      "weight": 2,
      "article_count": 2,
      "source": "Real Salt Lake",
      "target": "Sporting Kansas City"
    }
  ]
}